overwatch_sayak/__init__.py
overwatch_sayak/annotators/__init__.py
overwatch_sayak/annotators/base.py
overwatch_sayak/annotators/core.py
overwatch_sayak/annotators/utils.py
overwatch_sayak/classification/__init__.py
overwatch_sayak/classification/core.py
overwatch_sayak/config.py
overwatch_sayak/dataset/__init__.py
overwatch_sayak/dataset/core.py
overwatch_sayak/dataset/formats/__init__.py
overwatch_sayak/dataset/formats/coco.py
overwatch_sayak/dataset/formats/pascal_voc.py
overwatch_sayak/dataset/formats/yolo.py
overwatch_sayak/dataset/utils.py
overwatch_sayak/detection/__init__.py
overwatch_sayak/detection/annotate.py
overwatch_sayak/detection/core.py
overwatch_sayak/detection/line_zone.py
overwatch_sayak/detection/lmm.py
overwatch_sayak/detection/overlap_filter.py
overwatch_sayak/detection/tools/__init__.py
overwatch_sayak/detection/tools/csv_sink.py
overwatch_sayak/detection/tools/inferenceslicer.py
overwatch_sayak/detection/tools/json_sink.py
overwatch_sayak/detection/tools/polygon_zone.py
overwatch_sayak/detection/tools/smoother.py
overwatch_sayak/detection/utils.py
overwatch_sayak/draw/__init__.py
overwatch_sayak/draw/color.py
overwatch_sayak/draw/utils.py
overwatch_sayak/geometry/__init__.py
overwatch_sayak/geometry/core.py
overwatch_sayak/geometry/utils.py
overwatch_sayak/keypoint/__init__.py
overwatch_sayak/keypoint/annotators.py
overwatch_sayak/keypoint/core.py
overwatch_sayak/keypoint/skeletons.py
overwatch_sayak/metrics/__init__.py
overwatch_sayak/metrics/detection.py
overwatch_sayak/tracker/__init__.py
overwatch_sayak/tracker/track/__init__.py
overwatch_sayak/tracker/track/basetrack.py
overwatch_sayak/tracker/track/core.py
overwatch_sayak/tracker/track/kalmann_filter.py
overwatch_sayak/tracker/track/matching.py
overwatch_sayak/utils/__init__.py
overwatch_sayak/utils/conversion.py
overwatch_sayak/utils/file.py
overwatch_sayak/utils/image.py
overwatch_sayak/utils/internal.py
overwatch_sayak/utils/iterables.py
overwatch_sayak/utils/notebook.py
overwatch_sayak-1.0.3.dist-info/LICENSE.md
overwatch_sayak-1.0.3.dist-info/METADATA
overwatch_sayak-1.0.3.dist-info/WHEEL
overwatch_sayak-1.0.3.dist-info/RECORD
